prefect_slack/__init__.py
prefect_slack/_version.py
prefect_slack/credentials.py
prefect_slack/messages.py
prefect_slack-0.3.1.dist-info/LICENSE
prefect_slack-0.3.1.dist-info/METADATA
prefect_slack-0.3.1.dist-info/WHEEL
prefect_slack-0.3.1.dist-info/entry_points.txt
prefect_slack-0.3.1.dist-info/top_level.txt
prefect_slack-0.3.1.dist-info/RECORD
