Metadata-Version: 2.1
Name: prefect-slack
Version: 0.3.1
Summary: Prefect integrations with Slack
Author-email: "Prefect Technologies, Inc." <help@prefect.io>
License: Apache License 2.0
Project-URL: Homepage, https://github.com/PrefectHQ/prefect/tree/main/src/integrations/prefect-slack
Keywords: prefect
Classifier: Natural Language :: English
Classifier: Intended Audience :: Developers
Classifier: Intended Audience :: System Administrators
Classifier: License :: OSI Approved :: Apache Software License
Classifier: Programming Language :: Python :: 3 :: Only
Classifier: Programming Language :: Python :: 3.9
Classifier: Programming Language :: Python :: 3.10
Classifier: Programming Language :: Python :: 3.11
Classifier: Programming Language :: Python :: 3.12
Classifier: Topic :: Software Development :: Libraries
Requires-Python: >=3.9
License-File: LICENSE
Requires-Dist: aiohttp
Requires-Dist: slack-sdk>=3.15.1
Requires-Dist: prefect>=3.0.0
Provides-Extra: dev
Requires-Dist: coverage; extra == "dev"
Requires-Dist: interrogate; extra == "dev"
Requires-Dist: mkdocs-gen-files; extra == "dev"
Requires-Dist: mkdocs-material; extra == "dev"
Requires-Dist: mkdocs; extra == "dev"
Requires-Dist: mkdocstrings[python]; extra == "dev"
Requires-Dist: mypy; extra == "dev"
Requires-Dist: pillow; extra == "dev"
Requires-Dist: pre-commit; extra == "dev"
Requires-Dist: pytest-asyncio; extra == "dev"
Requires-Dist: pytest>=8.3; extra == "dev"
Requires-Dist: pytest-env; extra == "dev"
Requires-Dist: pytest-xdist; extra == "dev"
